tonydbc/__init__.py
tonydbc/audit_table.sql
tonydbc/config.toml
tonydbc/create_test_database.py
tonydbc/dataframe_fast.py
tonydbc/env_utils.py
tonydbc/mqtt_client.py
tonydbc/tony_utils.py
tonydbc/tonydbc.py
tonydbc-1.3.11.dist-info/licenses/LICENSE
tonydbc-1.3.11.dist-info/METADATA
tonydbc-1.3.11.dist-info/WHEEL
tonydbc-1.3.11.dist-info/top_level.txt
tonydbc-1.3.11.dist-info/RECORD
