Metadata-Version: 2.4
Name: tonydbc
Version: 1.3.11
Summary: A high-level database connector for MariaDB
Author-email: Michael Currie <mcurrie@gmail.com>
License-Expression: MIT
Project-URL: Homepage, https://github.com/Fling-Asia/tonydbc
Keywords: mariadb,database,connector,ODBC,pandas
Classifier: Programming Language :: Python
Classifier: Programming Language :: Python :: 3
Requires-Python: <4.0,>=3.10
License-File: LICENSE
Requires-Dist: iteration_utilities
Requires-Dist: python-dotenv
Requires-Dist: more-itertools
Requires-Dist: jsonschema
Requires-Dist: requests
Requires-Dist: numpy>=1.23.5
Requires-Dist: pandas
Requires-Dist: paho-mqtt>=1.6.1
Requires-Dist: mariadb
Requires-Dist: clipman
Requires-Dist: tzlocal
Requires-Dist: filelock
Requires-Dist: uuid6
Provides-Extra: dev
Requires-Dist: bumpver; extra == "dev"
Requires-Dist: isort; extra == "dev"
Requires-Dist: pip-tools; extra == "dev"
Requires-Dist: pytest; extra == "dev"
Requires-Dist: mypy>=1.10; extra == "dev"
Requires-Dist: types-pytz; extra == "dev"
Requires-Dist: ruff; extra == "dev"
Requires-Dist: pandas-stubs; extra == "dev"
Requires-Dist: types-pytz; extra == "dev"
Requires-Dist: types-python-dateutil; extra == "dev"
Requires-Dist: types-docker; extra == "dev"
Requires-Dist: twine; extra == "dev"
Provides-Extra: test
Requires-Dist: pytest>=7.0.0; extra == "test"
Requires-Dist: testcontainers>=4.0.0; extra == "test"
Requires-Dist: mariadb>=1.1.0; extra == "test"
Dynamic: license-file
